chatads_sdk/__init__.py
chatads_sdk/client.py
chatads_sdk/exceptions.py
chatads_sdk/models.py
chatads_sdk-0.1.13.dist-info/METADATA
chatads_sdk-0.1.13.dist-info/WHEEL
chatads_sdk-0.1.13.dist-info/top_level.txt
chatads_sdk-0.1.13.dist-info/RECORD
