Metadata-Version: 2.4
Name: chatads-sdk
Version: 0.1.13
Summary: Lightweight Python client for the ChatAds affiliate scoring API
Author-email: ChatAds <support@getchatads.com>
License: MIT
Project-URL: Homepage, https://github.com/Chat-Ads/chatads-python-sdk
Project-URL: Repository, https://github.com/Chat-Ads/chatads-python-sdk
Project-URL: Changelog, https://github.com/Chat-Ads/chatads-python-sdk/releases
Keywords: chatads,sdk,ads,automation
Classifier: Intended Audience :: Developers
Classifier: License :: OSI Approved :: MIT License
Classifier: Programming Language :: Python :: 3
Classifier: Programming Language :: Python :: 3.9
Classifier: Programming Language :: Python :: 3.10
Classifier: Programming Language :: Python :: 3.11
Classifier: Programming Language :: Python :: 3.12
Classifier: Topic :: Internet :: WWW/HTTP :: Dynamic Content
Requires-Python: >=3.9
Requires-Dist: httpx<1.0,>=0.27
Provides-Extra: async
Requires-Dist: httpx[http2]<1.0,>=0.27; extra == "async"
